beatsynchr/__init__.py
beatsynchr/core.py
beatsynchr-0.1.2.dist-info/licenses/LICENSE
beatsynchr-0.1.2.dist-info/licenses/LICENSE_THIRD_PARTY
beatsynchr-0.1.2.dist-info/METADATA
beatsynchr-0.1.2.dist-info/WHEEL
beatsynchr-0.1.2.dist-info/top_level.txt
beatsynchr-0.1.2.dist-info/RECORD
