Metadata-Version: 2.4
Name: beatsynchr
Version: 0.1.2
Summary: A Python library for syncing images and videos with music beats
Author: Jakub Nurkiewicz
Author-email: Jakub Nurkiewicz <jakub.nurkiewicz.2003@gmail.com>
Keywords: images processing,video processing,music beats
Classifier: Programming Language :: Python :: 3.12
Requires-Python: >=3.12
License-File: LICENSE
License-File: LICENSE_THIRD_PARTY
Requires-Dist: librosa>=0.11.0
Requires-Dist: numpy>=2.0.0
Requires-Dist: moviepy>=2.0.0
Requires-Dist: Pillow>=11.0.0
Requires-Dist: pillow-heif>=1.0.0
Dynamic: author
Dynamic: license-file
